LICENSE
MANIFEST.in
README.rst
setup.cfg
setup.py
pytag/__init__.py
pytag/codecs.py
pytag/constants.py
pytag/containers.py
pytag/formats.py
pytag/interface.py
pytag/structures.py
pytag/utils.py
pytag.egg-info/PKG-INFO
pytag.egg-info/SOURCES.txt
pytag.egg-info/dependency_links.txt
pytag.egg-info/requires.txt
pytag.egg-info/top_level.txt