Metadata-Version: 1.1
Name: pytag
Version: 0.1.4
Summary: A library to handle audio metadata
Home-page: http://jlesquembre.github.io/pytag/
Author: José Luis Lafuente
Author-email: jlesquembre@gmail.com
License: GNU General Public License v3 (GPLv3)
Keywords: audio,metadata
Platform: UNKNOWN
Classifier: Development Status :: 3 - Alpha
Classifier: Topic :: Multimedia :: Sound/Audio
Classifier: Topic :: Utilities
Classifier: Intended Audience :: Developers
Classifier: License :: OSI Approved :: GNU General Public License v3 (GPLv3)
Classifier: Operating System :: OS Independent
Classifier: Programming Language :: Python
Classifier: Programming Language :: Python :: 3.3
